nbhugoexporter/__init__.py
nbhugoexporter/hugo_markdown.tpl
nbhugoexporter/hugoexporter.py
nbhugoexporter/hugopreprocessor.py
nbhugoexporter-0.2.0.dist-info/DESCRIPTION.rst
nbhugoexporter-0.2.0.dist-info/METADATA
nbhugoexporter-0.2.0.dist-info/RECORD
nbhugoexporter-0.2.0.dist-info/WHEEL
nbhugoexporter-0.2.0.dist-info/entry_points.txt
nbhugoexporter-0.2.0.dist-info/metadata.json
nbhugoexporter-0.2.0.dist-info/top_level.txt
