Metadata-Version: 2.0
Name: nbhugoexporter
Version: 0.2.0
Summary: Export Jupyter notebooks to a Hugo compatible format
Home-page: https://github.com/jbandlow/nb_hugo_exporter
Author: Jason Bandlow
Author-email: jbandlow@gmail.com
License: UNKNOWN
Platform: UNKNOWN
Classifier: Programming Language :: Python :: 3
Classifier: License :: OSI Approved :: MIT License
Classifier: Operating System :: OS Independent
Requires-Dist: nbconvert
Requires-Dist: traitlets
